LICENSE
README.rst
setup.py
slearn/__init__.py
slearn/classifer.py
slearn/dmetric.py
slearn/mkc.py
slearn/nn_example_models.py
slearn/sgenerate.py
slearn/simulation.py
slearn/symbols.py
slearn.egg-info/PKG-INFO
slearn.egg-info/SOURCES.txt
slearn.egg-info/dependency_links.txt
slearn.egg-info/requires.txt
slearn.egg-info/top_level.txt