Metadata-Version: 2.4
Name: slearn
Version: 0.2.7
Summary: A package linking symbolic representation with sklearn for time series prediction
Home-page: https://github.com/nla-group/slearn
Author: Roberto Cahuantzi, Xinye Chen, Stefan Güttel
Author-email: stefan.guettel@manchester.ac.uk
Maintainer: NLA Group
Maintainer-email: stefan.guettel@manchester.ac.uk
License: MIT
Classifier: Intended Audience :: Science/Research
Classifier: Intended Audience :: Developers
Classifier: Programming Language :: Python :: 3
Classifier: Programming Language :: Python :: 3.7
Classifier: Programming Language :: Python :: 3.8
Classifier: Programming Language :: Python :: 3.9
Classifier: Programming Language :: Python :: 3.10
Classifier: Topic :: Software Development
Classifier: Topic :: Scientific/Engineering
Classifier: Operating System :: Microsoft :: Windows
Classifier: Operating System :: Unix
Classifier: License :: OSI Approved :: MIT License
Requires-Python: >=3.7
License-File: LICENSE
Requires-Dist: numpy>=1.17.2
Requires-Dist: scikit-learn>=1.0.0
Requires-Dist: pandas>=1.0.0
Requires-Dist: requests>=2.25.0
Requires-Dist: torch>=1.7.0
Dynamic: author
Dynamic: author-email
Dynamic: classifier
Dynamic: description
Dynamic: description-content-type
Dynamic: home-page
Dynamic: license
Dynamic: license-file
Dynamic: maintainer
Dynamic: maintainer-email
Dynamic: requires-dist
Dynamic: requires-python
Dynamic: summary
